subenum.py
subenum/subenum.py
subenum-1.5.dist-info/METADATA
subenum-1.5.dist-info/WHEEL
subenum-1.5.dist-info/entry_points.txt
subenum-1.5.dist-info/top_level.txt
subenum-1.5.dist-info/RECORD
